odoo/addons/account_payment_term_security/README.rst
odoo/addons/account_payment_term_security/__init__.py
odoo/addons/account_payment_term_security/__manifest__.py
odoo/addons/account_payment_term_security/i18n/account_payment_term_security.pot
odoo/addons/account_payment_term_security/i18n/es.po
odoo/addons/account_payment_term_security/models/__init__.py
odoo/addons/account_payment_term_security/models/account_move.py
odoo/addons/account_payment_term_security/models/res_partner.py
odoo/addons/account_payment_term_security/readme/CONFIGURE.rst
odoo/addons/account_payment_term_security/readme/CONTRIBUTORS.rst
odoo/addons/account_payment_term_security/readme/DESCRIPTION.rst
odoo/addons/account_payment_term_security/security/security.xml
odoo/addons/account_payment_term_security/static/description/icon.png
odoo/addons/account_payment_term_security/static/description/index.html
odoo/addons/account_payment_term_security/tests/__init__.py
odoo/addons/account_payment_term_security/tests/test_account_payment_term_security.py
odoo13_addon_account_payment_term_security-13.0.1.0.1.dev4.dist-info/METADATA
odoo13_addon_account_payment_term_security-13.0.1.0.1.dev4.dist-info/WHEEL
odoo13_addon_account_payment_term_security-13.0.1.0.1.dev4.dist-info/top_level.txt
odoo13_addon_account_payment_term_security-13.0.1.0.1.dev4.dist-info/RECORD
